untiler/__init__.py
untiler/scripts/__init__.py
untiler/scripts/cli.py
untiler/scripts/mbtiles_extract.py
untiler/scripts/tile_utils.py
untiler-0.2.1.dist-info/DESCRIPTION.rst
untiler-0.2.1.dist-info/METADATA
untiler-0.2.1.dist-info/RECORD
untiler-0.2.1.dist-info/WHEEL
untiler-0.2.1.dist-info/entry_points.txt
untiler-0.2.1.dist-info/metadata.json
untiler-0.2.1.dist-info/top_level.txt
