Metadata-Version: 2.0
Name: untiler
Version: 0.2.1
Summary: Combine image tiles into composite TIFs
Home-page: https://github.com/mapbox/untiler
Author: Damon Burgett
Author-email: damon@mapbox.com
License: MIT
Platform: UNKNOWN
Requires-Dist: click
Requires-Dist: rasterio
Requires-Dist: mercantile
Requires-Dist: mbutil
Provides-Extra: test
Requires-Dist: pytest; extra == 'test'
Requires-Dist: pytest-cov; extra == 'test'
